docs/__init__.py
docs/conf.py
tests/__init__.py
tests/conftest.py
tests/test_colombia.py
tests/test_mexico.py
tests/test_singleton.py
tests/calculators/__init__.py
tests/calculators/test_fixed_holiday_calculator.py
tests/calculators/test_moving_holiday_calculator.py
tests/calculators/test_position_day_holiday_calculator.py
workingless/__init__.py
workingless/constants.py
workingless/holiday.py
workingless/holiday_calculator.py
workingless/utils.py
workingless/calculators/__init__.py
workingless/calculators/easter_calculator.py
workingless/calculators/every_n_years_calculator.py
workingless/calculators/fixed_calculator.py
workingless/calculators/moving_calculator.py
workingless/calculators/position_day_calculator.py
workingless/countries/__init__.py
workingless/countries/col.py
workingless/countries/country_base.py
workingless/countries/mex.py
workingless/holiday_calculators/__init__.py
workingless/holiday_calculators/easter_holiday_calculator.py
workingless/holiday_calculators/fixed_holiday_calculator.py
workingless/holiday_calculators/moving_holiday_calculator.py
workingless-0.2.1.dist-info/LICENSE
workingless-0.2.1.dist-info/METADATA
workingless-0.2.1.dist-info/WHEEL
workingless-0.2.1.dist-info/top_level.txt
workingless-0.2.1.dist-info/RECORD
