Metadata-Version: 2.1
Name: workingless
Version: 0.2.1
Summary: Holidays and working days calculations
Home-page: https://github.com/pity7736/workingless
Author: Julián Cortés
Author-email: pity7736@gmail.com
License: UNKNOWN
Keywords: holiday working-day
Platform: UNKNOWN
Classifier: Development Status :: 3 - Alpha
Classifier: Intended Audience :: Developers
Classifier: License :: OSI Approved :: GNU Lesser General Public License v3 (LGPLv3)
Classifier: Operating System :: OS Independent
Classifier: Programming Language :: Python :: 3
Classifier: Programming Language :: Python :: 3.7
Classifier: Topic :: Utilities
Requires-Dist: python-dateutil (==2.8.1)
